examples/__init__.py
examples/adjustments.py
examples/catalog_management.py
examples/event_polling.py
examples/get_products.py
examples/logger.py
examples/webhook_verification.py
paddle_billing/Client.py
paddle_billing/EnumStringify.py
paddle_billing/Environment.py
paddle_billing/FiltersNone.py
paddle_billing/FiltersUndefined.py
paddle_billing/HasParameters.py
paddle_billing/Operation.py
paddle_billing/Options.py
paddle_billing/PaddleStrEnum.py
paddle_billing/RecursivelyRemoveKey.py
paddle_billing/ResponseParser.py
paddle_billing/Undefined.py
paddle_billing/__init__.py
paddle_billing/Entities/Address.py
paddle_billing/Entities/Adjustment.py
paddle_billing/Entities/AdjustmentCreditNote.py
paddle_billing/Entities/Business.py
paddle_billing/Entities/ClientToken.py
paddle_billing/Entities/CreditBalance.py
paddle_billing/Entities/Customer.py
paddle_billing/Entities/CustomerAuthToken.py
paddle_billing/Entities/CustomerPortalSession.py
paddle_billing/Entities/DateTime.py
paddle_billing/Entities/Discount.py
paddle_billing/Entities/DiscountGroup.py
paddle_billing/Entities/Entity.py
paddle_billing/Entities/Event.py
paddle_billing/Entities/EventType.py
paddle_billing/Entities/IPAddresses.py
paddle_billing/Entities/Notification.py
paddle_billing/Entities/NotificationLog.py
paddle_billing/Entities/NotificationSetting.py
paddle_billing/Entities/PaymentMethod.py
paddle_billing/Entities/Price.py
paddle_billing/Entities/PricePreview.py
paddle_billing/Entities/Product.py
paddle_billing/Entities/Report.py
paddle_billing/Entities/ReportCSV.py
paddle_billing/Entities/Simulation.py
paddle_billing/Entities/SimulationRun.py
paddle_billing/Entities/SimulationRunEvent.py
paddle_billing/Entities/SimulationType.py
paddle_billing/Entities/Subscription.py
paddle_billing/Entities/SubscriptionPreview.py
paddle_billing/Entities/Transaction.py
paddle_billing/Entities/TransactionData.py
paddle_billing/Entities/TransactionPreview.py
paddle_billing/Entities/__init__.py
paddle_python_sdk-1.12.0.dist-info/licenses/LICENSE
paddle_python_sdk-1.12.0.dist-info/METADATA
paddle_python_sdk-1.12.0.dist-info/WHEEL
paddle_python_sdk-1.12.0.dist-info/top_level.txt
paddle_python_sdk-1.12.0.dist-info/RECORD
