Metadata-Version: 2.4
Name: paddle-python-sdk
Version: 1.12.0
Summary: Paddle's Python SDK for Paddle Billing
Home-page: https://developer.paddle.com/api-reference/overview
Author: Paddle and contributors
Author-email: team-dx@paddle.com
License: Apache-2.0
Keywords: paddle,sdk,python
Classifier: Development Status :: 4 - Beta
Classifier: Intended Audience :: Developers
Classifier: License :: OSI Approved :: MIT License
Classifier: Programming Language :: Python :: 3.11
Classifier: Programming Language :: Python :: 3.12
Classifier: Programming Language :: Python :: 3.13
Requires-Python: >=3.11
License-File: LICENSE
Requires-Dist: requests>=2.31
Requires-Dist: urllib3>=1.26.18
Provides-Extra: dev
Requires-Dist: pytest<9.1.0,>=7.4.4; extra == "dev"
Requires-Dist: pytest-cov<7.1,>=4.1; extra == "dev"
Requires-Dist: requests-mock~=1.11.0; extra == "dev"
Requires-Dist: setuptools>=69.0.3; extra == "dev"
Requires-Dist: pre-commit>=3.8.0; extra == "dev"
Requires-Dist: black>=24.8.0; extra == "dev"
Requires-Dist: flake8>=7.1.1; extra == "dev"
Dynamic: author
Dynamic: author-email
Dynamic: classifier
Dynamic: description
Dynamic: description-content-type
Dynamic: home-page
Dynamic: keywords
Dynamic: license
Dynamic: license-file
Dynamic: provides-extra
Dynamic: requires-dist
Dynamic: requires-python
Dynamic: summary
